{
  "sprites": [
    {
      "name": "grass",
      "image": {
        "filepath": "C:/Users/fnelf/Documents/java projects/engine/src/main/resources/grass.png",
        "width": 16,
        "height": 16
      }
    },
    {
      "name": "down2",
      "image": {
        "filepath": "C:/Users/fnelf/Documents/java projects/engine/src/main/resources/down2.png",
        "width": 16,
        "height": 16
      }
    }
  ],
  "rooms": [
    {
      "name":"room1",
      "layers": [
        {
          "type": "background",
          "name": "grass",
          "sprite": "grass"
        },
        {
          "type": "background",
          "name": "grass2",
          "sprite": "grass"
        }
      ]

    }
  ]
}